README.txt
setup.cfg
setup.py
globe/__init__.py
globe.egg-info/PKG-INFO
globe.egg-info/SOURCES.txt
globe.egg-info/dependency_links.txt
globe.egg-info/requires.txt
globe.egg-info/top_level.txt
globe/connect/__init__.py
globe/connect/amax.py
globe/connect/location.py
globe/connect/oauth.py
globe/connect/payment.py
globe/connect/sms.py
globe/connect/subscriber.py
globe/connect/ussd.py
globe/connect/voice.py
globe/connect/voiceLib/__init__.py
globe/connect/voiceLib/ask.py
globe/connect/voiceLib/call.py
globe/connect/voiceLib/choices.py
globe/connect/voiceLib/conference.py
globe/connect/voiceLib/hangup.py
globe/connect/voiceLib/joinPrompt.py
globe/connect/voiceLib/leavePrompt.py
globe/connect/voiceLib/machineDetection.py
globe/connect/voiceLib/message.py
globe/connect/voiceLib/on.py
globe/connect/voiceLib/record.py
globe/connect/voiceLib/redirect.py
globe/connect/voiceLib/result.py
globe/connect/voiceLib/say.py
globe/connect/voiceLib/session.py
globe/connect/voiceLib/startRecording.py
globe/connect/voiceLib/transcription.py
globe/connect/voiceLib/transfer.py
globe/connect/voiceLib/wait.py