Metadata-Version: 1.1
Name: globe
Version: 1.0.4
Summary: Globe Api 
Home-page: https://github.com/globelabs/globe-connect-python
Author: clark galgo
Author-email: clark21@dev-engine.net
License: UNKNOWN
Download-URL: https://github.com/globelabs/globe-connect-python/archive/master.zip
Keywords: Globe,Globe Api,Globe Labs
Platform: UNKNOWN
